[
  {
    "id": "math204-t7-drill-1",
    "subjectId": "math204",
    "topicId": "math204-7",
    "type": "written",
    "difficulty": 1,
    "title": "Drill: Power Series Form",
    "description": "Write the general form of a power series centered at $c$.",
    "hints": [
      "Include the summation notation."
    ],
    "solution": "$\\sum_{n=0}^\\infty a_n(x-c)^n$"
  },
  {
    "id": "math204-t7-drill-2",
    "subjectId": "math204",
    "topicId": "math204-7",
    "type": "written",
    "difficulty": 1,
    "title": "Drill: Maclaurin vs Taylor",
    "description": "What is the difference between a Maclaurin series and a Taylor series?",
    "hints": [
      "Consider the center point."
    ],
    "solution": "A Maclaurin series is a Taylor series centered at $a = 0$."
  },
  {
    "id": "math204-t7-drill-3",
    "subjectId": "math204",
    "topicId": "math204-7",
    "type": "written",
    "difficulty": 1,
    "title": "Drill: Taylor Series Formula",
    "description": "Write the formula for the Taylor series of $f(x)$ centered at $a$.",
    "hints": [
      "Include derivatives."
    ],
    "solution": "$\\sum_{n=0}^\\infty \\frac{f^{(n)}(a)}{n!}(x-a)^n$"
  },
  {
    "id": "math204-t7-drill-4",
    "subjectId": "math204",
    "topicId": "math204-7",
    "type": "written",
    "difficulty": 1,
    "title": "Drill: Radius of Convergence",
    "description": "What does the radius of convergence tell us?",
    "hints": [
      "Where does the series converge?"
    ],
    "solution": "The radius $R$ gives the interval $(c-R, c+R)$ where the power series converges."
  },
  {
    "id": "math204-t7-ex01",
    "subjectId": "math204",
    "topicId": "math204-7",
    "type": "written",
    "difficulty": 2,
    "title": "Radius of Convergence",
    "description": "Find the radius of convergence for $\\sum_{n=0}^\\infty \\frac{x^n}{n!}$.",
    "hints": [
      "Use the Ratio Test."
    ],
    "solution": "$a_n = \\frac{1}{n!}$\\n\\n$\\lim_{n \\to \\infty} \\left|\\frac{a_{n+1}}{a_n}\\right| = \\lim_{n \\to \\infty} \\frac{n!}{(n+1)!} = \\lim_{n \\to \\infty} \\frac{1}{n+1} = 0$\\n\\n$L|x| = 0 < 1$ for all $x$, so the radius of convergence is $R = \\infty$."
  },
  {
    "id": "math204-t7-ex02",
    "subjectId": "math204",
    "topicId": "math204-7",
    "type": "written",
    "difficulty": 3,
    "title": "Interval of Convergence",
    "description": "Find the interval of convergence for $\\sum_{n=1}^\\infty \\frac{x^n}{n}$.",
    "hints": [
      "Use Ratio Test, then check endpoints."
    ],
    "solution": "Ratio Test:\\n$L = \\lim_{n \\to \\infty} \\left|\\frac{a_{n+1}x^{n+1}}{a_n x^n}\\right| = \\lim_{n \\to \\infty} \\frac{n}{n+1}|x| = |x|$\\n\\nConverges when $|x| < 1$, so $R = 1$.\\n\\nCheck endpoints:\\nAt $x = 1$: $\\sum \\frac{1}{n}$ diverges (harmonic series).\\nAt $x = -1$: $\\sum \\frac{(-1)^n}{n}$ converges (alternating harmonic).\\n\\n**Interval of convergence**: $[-1, 1)$"
  },
  {
    "id": "math204-t7-ex03",
    "subjectId": "math204",
    "topicId": "math204-7",
    "type": "written",
    "difficulty": 2,
    "title": "Geometric Series as Power Series",
    "description": "Express $\\frac{1}{1-x}$ as a power series and state its radius of convergence.",
    "hints": [
      "Use the geometric series formula."
    ],
    "solution": "$\\frac{1}{1-x} = \\sum_{n=0}^\\infty x^n$ for $|x| < 1$\\n\\n**Radius of convergence**: $R = 1$"
  },
  {
    "id": "math204-t7-ex04",
    "subjectId": "math204",
    "topicId": "math204-7",
    "type": "written",
    "difficulty": 3,
    "title": "Maclaurin Series for e^x",
    "description": "Derive the first 4 terms of the Maclaurin series for $f(x) = e^x$.",
    "hints": [
      "Compute $f(0), f'(0), f''(0), f'''(0)$."
    ],
    "solution": "$f(x) = e^x, f(0) = 1$\\n$f'(x) = e^x, f'(0) = 1$\\n$f''(x) = e^x, f''(0) = 1$\\n$f'''(x) = e^x, f'''(0) = 1$\\n\\n$e^x = 1 + \\frac{x}{1!} + \\frac{x^2}{2!} + \\frac{x^3}{3!} + \\cdots = \\sum_{n=0}^\\infty \\frac{x^n}{n!}$\\n\\nFirst 4 terms: $1 + x + \\frac{x^2}{2} + \\frac{x^3}{6}$"
  },
  {
    "id": "math204-t7-ex05",
    "subjectId": "math204",
    "topicId": "math204-7",
    "type": "written",
    "difficulty": 3,
    "title": "Maclaurin Series for sin(x)",
    "description": "Write the Maclaurin series for $\\sin x$.",
    "hints": [
      "Derivatives of sine cycle through sine and cosine."
    ],
    "solution": "$f(x) = \\sin x, f(0) = 0$\\n$f'(x) = \\cos x, f'(0) = 1$\\n$f''(x) = -\\sin x, f''(0) = 0$\\n$f'''(x) = -\\cos x, f'''(0) = -1$\\n$f^{(4)}(x) = \\sin x, f^{(4)}(0) = 0$\\n\\nPattern: only odd powers, alternating signs\\n\\n$\\sin x = \\sum_{n=0}^\\infty \\frac{(-1)^n x^{2n+1}}{(2n+1)!} = x - \\frac{x^3}{3!} + \\frac{x^5}{5!} - \\frac{x^7}{7!} + \\cdots$"
  },
  {
    "id": "math204-t7-ex06",
    "subjectId": "math204",
    "topicId": "math204-7",
    "type": "written",
    "difficulty": 3,
    "title": "Maclaurin Series for cos(x)",
    "description": "Write the Maclaurin series for $\\cos x$.",
    "hints": [
      "Similar to sine, but starts differently."
    ],
    "solution": "$f(x) = \\cos x, f(0) = 1$\\n$f'(x) = -\\sin x, f'(0) = 0$\\n$f''(x) = -\\cos x, f''(0) = -1$\\n$f'''(x) = \\sin x, f'''(0) = 0$\\n\\nPattern: only even powers, alternating signs\\n\\n$\\cos x = \\sum_{n=0}^\\infty \\frac{(-1)^n x^{2n}}{(2n)!} = 1 - \\frac{x^2}{2!} + \\frac{x^4}{4!} - \\frac{x^6}{6!} + \\cdots$"
  },
  {
    "id": "math204-t7-ex07",
    "subjectId": "math204",
    "topicId": "math204-7",
    "type": "written",
    "difficulty": 4,
    "title": "Taylor Polynomial Approximation",
    "description": "Find the 3rd degree Taylor polynomial for $f(x) = \\ln x$ centered at $a = 1$.",
    "hints": [
      "Compute derivatives at $x = 1$."
    ],
    "solution": "$f(x) = \\ln x, f(1) = 0$\\n$f'(x) = \\frac{1}{x}, f'(1) = 1$\\n$f''(x) = -\\frac{1}{x^2}, f''(1) = -1$\\n$f'''(x) = \\frac{2}{x^3}, f'''(1) = 2$\\n\\n$P_3(x) = 0 + 1(x-1) + \\frac{-1}{2!}(x-1)^2 + \\frac{2}{3!}(x-1)^3$\\n\\n$= (x-1) - \\frac{(x-1)^2}{2} + \\frac{(x-1)^3}{3}$"
  },
  {
    "id": "math204-t7-ex08",
    "subjectId": "math204",
    "topicId": "math204-7",
    "type": "written",
    "difficulty": 4,
    "title": "Operations on Power Series",
    "description": "Find the power series for $f(x) = \\frac{1}{1+x^2}$ by modifying the geometric series.",
    "hints": [
      "Use $\\frac{1}{1-u} = \\sum u^n$ with $u = -x^2$."
    ],
    "solution": "$\\frac{1}{1+x^2} = \\frac{1}{1-(-x^2)} = \\sum_{n=0}^\\infty (-x^2)^n = \\sum_{n=0}^\\infty (-1)^n x^{2n}$\\n\\n$= 1 - x^2 + x^4 - x^6 + \\cdots$ for $|x| < 1$"
  },
  {
    "id": "math204-t7-ex09",
    "subjectId": "math204",
    "topicId": "math204-7",
    "type": "written",
    "difficulty": 4,
    "title": "Integration of Power Series",
    "description": "Find the power series for $\\arctan x$ by integrating the series for $\\frac{1}{1+x^2}$.",
    "hints": [
      "$\\arctan x = \\int \\frac{1}{1+x^2} \\, dx$."
    ],
    "solution": "From previous: $\\frac{1}{1+x^2} = \\sum_{n=0}^\\infty (-1)^n x^{2n}$\\n\\nIntegrate term by term:\\n$\\arctan x = \\int \\sum_{n=0}^\\infty (-1)^n x^{2n} \\, dx = \\sum_{n=0}^\\infty \\frac{(-1)^n x^{2n+1}}{2n+1} + C$\\n\\nUsing $\\arctan(0) = 0$, we have $C = 0$.\\n\\n$\\arctan x = \\sum_{n=0}^\\infty \\frac{(-1)^n x^{2n+1}}{2n+1} = x - \\frac{x^3}{3} + \\frac{x^5}{5} - \\frac{x^7}{7} + \\cdots$"
  },
  {
    "id": "math204-t7-ex10",
    "subjectId": "math204",
    "topicId": "math204-7",
    "type": "written",
    "difficulty": 5,
    "title": "Differentiation of Power Series",
    "description": "Find the power series for $\\cos x$ by differentiating the series for $\\sin x$.",
    "hints": [
      "Differentiate $\\sin x = \\sum \\frac{(-1)^n x^{2n+1}}{(2n+1)!}$ term by term."
    ],
    "solution": "$\\sin x = \\sum_{n=0}^\\infty \\frac{(-1)^n x^{2n+1}}{(2n+1)!}$\\n\\nDifferentiate:\\n$\\cos x = \\frac{d}{dx}[\\sin x] = \\sum_{n=0}^\\infty \\frac{(-1)^n (2n+1)x^{2n}}{(2n+1)!} = \\sum_{n=0}^\\infty \\frac{(-1)^n x^{2n}}{(2n)!}$\\n\\n$= 1 - \\frac{x^2}{2!} + \\frac{x^4}{4!} - \\cdots$"
  },
  {
    "id": "math204-t7-ex11",
    "subjectId": "math204",
    "topicId": "math204-7",
    "type": "written",
    "difficulty": 5,
    "title": "Error Estimation",
    "description": "Estimate $e^{0.5}$ using the 3rd degree Taylor polynomial and bound the error.",
    "hints": [
      "Use $P_3(x) = 1 + x + \\frac{x^2}{2} + \\frac{x^3}{6}$ and Lagrange remainder."
    ],
    "solution": "$P_3(0.5) = 1 + 0.5 + \\frac{(0.5)^2}{2} + \\frac{(0.5)^3}{6}$\\n$= 1 + 0.5 + 0.125 + 0.020833... \\approx 1.6458$\\n\\nError bound: $|R_3(x)| \\leq \\frac{M|x|^{n+1}}{(n+1)!}$ where $M = \\max|f^{(4)}(c)|$ for $c$ between 0 and 0.5.\\n\\nSince $f^{(4)}(x) = e^x$ and $e^x < e^{0.5} < 2$ on $[0, 0.5]$, we have $M = 2$.\\n\\n$|R_3(0.5)| \\leq \\frac{2(0.5)^4}{4!} = \\frac{2 \\cdot 0.0625}{24} = \\frac{0.125}{24} \\approx 0.0052$\\n\\nSo $e^{0.5} \\approx 1.6458 \\pm 0.0052$ (actual: $e^{0.5} \\approx 1.6487$)"
  },
  {
    "id": "math204-t7-ex12",
    "subjectId": "math204",
    "topicId": "math204-7",
    "type": "written",
    "difficulty": 5,
    "title": "Challenge: Binomial Series",
    "description": "Find the first 4 terms of the Maclaurin series for $f(x) = \\sqrt{1+x}$.",
    "hints": [
      "Use the binomial series $(1+x)^{1/2}$ or compute derivatives."
    ],
    "solution": "Method 1 - Derivatives:\\n$f(x) = (1+x)^{1/2}, f(0) = 1$\\n$f'(x) = \\frac{1}{2}(1+x)^{-1/2}, f'(0) = \\frac{1}{2}$\\n$f''(x) = -\\frac{1}{4}(1+x)^{-3/2}, f''(0) = -\\frac{1}{4}$\\n$f'''(x) = \\frac{3}{8}(1+x)^{-5/2}, f'''(0) = \\frac{3}{8}$\\n\\n$\\sqrt{1+x} = 1 + \\frac{1}{2}x + \\frac{-1/4}{2!}x^2 + \\frac{3/8}{3!}x^3 + \\cdots$\\n\\n$= 1 + \\frac{x}{2} - \\frac{x^2}{8} + \\frac{x^3}{16} - \\cdots$\\n\\nMethod 2 - Binomial Series:\\n$(1+x)^{1/2} = \\sum_{n=0}^\\infty \\binom{1/2}{n}x^n = 1 + \\frac{1}{2}x + \\frac{(1/2)(-1/2)}{2!}x^2 + \\frac{(1/2)(-1/2)(-3/2)}{3!}x^3 + \\cdots$"
  },
  {
    "id": "math204-t7-ex13",
    "subjectId": "math204",
    "topicId": "math204-7",
    "type": "written",
    "difficulty": 3,
    "title": "Manipulating Power Series",
    "description": "Find the power series for $f(x) = \\frac{1}{(1-x)^2}$ by differentiating the geometric series.",
    "hints": [
      "Start with $\\frac{1}{1-x} = \\sum_{n=0}^\\infty x^n$ for $|x| < 1$.",
      "Differentiate both sides with respect to $x$.",
      "What is $\\frac{d}{dx}\\left(\\frac{1}{1-x}\\right)$?"
    ],
    "solution": "Start with: $\\frac{1}{1-x} = \\sum_{n=0}^\\infty x^n = 1 + x + x^2 + x^3 + \\cdots$\n\nDifferentiate both sides:\n$\\frac{d}{dx}\\left(\\frac{1}{1-x}\\right) = \\frac{1}{(1-x)^2}$\n\n$\\frac{d}{dx}\\sum_{n=0}^\\infty x^n = \\sum_{n=1}^\\infty nx^{n-1} = 1 + 2x + 3x^2 + 4x^3 + \\cdots$\n\nTherefore:\n$\\frac{1}{(1-x)^2} = \\sum_{n=1}^\\infty nx^{n-1} = \\sum_{n=0}^\\infty (n+1)x^n$ for $|x| < 1$"
  },
  {
    "id": "math204-t7-ex14",
    "subjectId": "math204",
    "topicId": "math204-7",
    "type": "written",
    "difficulty": 4,
    "title": "Finding Limits Using Series",
    "description": "Use Taylor series to evaluate $\\lim_{x \\to 0} \\frac{\\sin x - x}{x^3}$.",
    "hints": [
      "Write the Maclaurin series for $\\sin x$.",
      "Subtract $x$ from the series.",
      "Divide by $x^3$ and take the limit."
    ],
    "solution": "The Maclaurin series for $\\sin x$ is:\n$\\sin x = x - \\frac{x^3}{3!} + \\frac{x^5}{5!} - \\frac{x^7}{7!} + \\cdots$\n\nSubtract $x$:\n$\\sin x - x = -\\frac{x^3}{6} + \\frac{x^5}{120} - \\cdots$\n\nDivide by $x^3$:\n$\\frac{\\sin x - x}{x^3} = -\\frac{1}{6} + \\frac{x^2}{120} - \\cdots$\n\nTaking the limit as $x \\to 0$:\n$\\lim_{x \\to 0} \\frac{\\sin x - x}{x^3} = -\\frac{1}{6}$"
  },
  {
    "id": "math204-t7-ex15",
    "subjectId": "math204",
    "topicId": "math204-7",
    "type": "written",
    "difficulty": 4,
    "title": "Series Multiplication",
    "description": "Find the first 4 terms of the Maclaurin series for $e^x \\cos x$.",
    "hints": [
      "Write out the first few terms of $e^x$ and $\\cos x$.",
      "Multiply the series together.",
      "Collect terms by power of $x$."
    ],
    "solution": "$e^x = 1 + x + \\frac{x^2}{2} + \\frac{x^3}{6} + \\cdots$\n\n$\\cos x = 1 - \\frac{x^2}{2} + \\frac{x^4}{24} - \\cdots$\n\nMultiply (collecting up to $x^3$):\n\n$e^x \\cos x = \\left(1 + x + \\frac{x^2}{2} + \\frac{x^3}{6}\\right)\\left(1 - \\frac{x^2}{2} + \\cdots\\right)$\n\n- Constant term: $1 \\cdot 1 = 1$\n- Coefficient of $x$: $x \\cdot 1 = x$\n- Coefficient of $x^2$: $1 \\cdot (-\\frac{1}{2}) + \\frac{1}{2} \\cdot 1 = 0$\n- Coefficient of $x^3$: $x \\cdot (-\\frac{x^2}{2}) + \\frac{x^3}{6} \\cdot 1 = -\\frac{x^3}{2} + \\frac{x^3}{6} = -\\frac{x^3}{3}$\n\n$e^x \\cos x = 1 + x - \\frac{x^3}{3} + \\cdots$"
  },
  {
    "id": "math204-t7-ex16",
    "subjectId": "math204",
    "topicId": "math204-7",
    "type": "written",
    "difficulty": 5,
    "title": "Challenge: Integration Using Series",
    "description": "Express $\\int_0^{0.5} \\frac{\\sin x}{x} \\, dx$ as an infinite series and estimate its value using the first 3 non-zero terms.",
    "hints": [
      "Write $\\frac{\\sin x}{x}$ as a power series by dividing the $\\sin x$ series by $x$.",
      "Integrate term by term from 0 to 0.5.",
      "Evaluate the first few terms numerically."
    ],
    "solution": "$\\sin x = x - \\frac{x^3}{6} + \\frac{x^5}{120} - \\frac{x^7}{5040} + \\cdots$\n\n$\\frac{\\sin x}{x} = 1 - \\frac{x^2}{6} + \\frac{x^4}{120} - \\frac{x^6}{5040} + \\cdots$\n\nIntegrate from 0 to $t$:\n$\\int_0^t \\frac{\\sin x}{x} \\, dx = t - \\frac{t^3}{18} + \\frac{t^5}{600} - \\frac{t^7}{35280} + \\cdots$\n\nSubstitute $t = 0.5$:\n- First term: $0.5 = 0.5$\n- Second term: $-\\frac{(0.5)^3}{18} = -\\frac{0.125}{18} \\approx -0.00694$\n- Third term: $\\frac{(0.5)^5}{600} = \\frac{0.03125}{600} \\approx 0.0000521$\n\nSum: $0.5 - 0.00694 + 0.0000521 \\approx 0.4931$\n\n(The actual value is approximately 0.4931...)"
  }
]
